daniyal_package/__init__.py
daniyal_new_package-0.1.0.dist-info/LICENSE
daniyal_new_package-0.1.0.dist-info/METADATA
daniyal_new_package-0.1.0.dist-info/WHEEL
daniyal_new_package-0.1.0.dist-info/top_level.txt
daniyal_new_package-0.1.0.dist-info/RECORD
