Metadata-Version: 2.1
Name: daniyal_new_package
Version: 0.1.0
Summary: This is the description of your package
Home-page: https://github.com/daniyalsaif/my_package
Author: Daniyal Saif
Author-email: daniyalsaif200@gmail.com
Classifier: Programming Language :: Python :: 3
Classifier: License :: OSI Approved :: MIT License
Classifier: Operating System :: OS Independent
Requires-Python: >=3.6
License-File: LICENSE
